{
    "key": "group_62dec2cf13f51",
    "title": "Block - Stats",
    "fields": [
        {
            "key": "field_62dec74b65bd6",
            "label": "<h2 style=\"text-align:center;\"> Stats <\/h2>",
            "name": "",
            "type": "message",
            "instructions": "",
            "required": 0,
            "conditional_logic": 0,
            "wrapper": {
                "width": "",
                "class": "",
                "id": ""
            },
            "message": "",
            "new_lines": "wpautop",
            "esc_html": 0
        },
        {
            "key": "field_62dec3d47bf6c",
            "label": "Kicker Text",
            "name": "elitedesign_blkstats_kckrtext",
            "type": "text",
            "instructions": "",
            "required": 0,
            "conditional_logic": 0,
            "wrapper": {
                "width": "",
                "class": "",
                "id": ""
            },
            "default_value": "",
            "placeholder": "",
            "prepend": "",
            "append": "",
            "maxlength": ""
        },
        {
            "key": "field_62dec38a7bf6a",
            "label": "Title",
            "name": "elitedesign_blkstats_title",
            "type": "text",
            "instructions": "",
            "required": 0,
            "conditional_logic": 0,
            "wrapper": {
                "width": "",
                "class": "",
                "id": ""
            },
            "default_value": "",
            "placeholder": "",
            "prepend": "",
            "append": "",
            "maxlength": ""
        },
        {
            "key": "field_62dec3c67bf6b",
            "label": "Expand For Options",
            "name": "",
            "type": "accordion",
            "instructions": "",
            "required": 0,
            "conditional_logic": 0,
            "wrapper": {
                "width": "",
                "class": "",
                "id": ""
            },
            "open": 0,
            "multi_expand": 0,
            "endpoint": 0
        },
        {
            "key": "field_62dec3eb7bf6d",
            "label": "Stats",
            "name": "elitedesign_blkstats_stats",
            "type": "repeater",
            "instructions": "",
            "required": 0,
            "conditional_logic": 0,
            "wrapper": {
                "width": "",
                "class": "",
                "id": ""
            },
            "collapsed": "",
            "min": 0,
            "max": 4,
            "layout": "block",
            "button_label": "Add Stat",
            "sub_fields": [
                {
                    "key": "field_62dec4097bf6e",
                    "label": "Value",
                    "name": "value",
                    "type": "text",
                    "instructions": "",
                    "required": 0,
                    "conditional_logic": 0,
                    "wrapper": {
                        "width": "",
                        "class": "",
                        "id": ""
                    },
                    "default_value": "",
                    "placeholder": "",
                    "prepend": "",
                    "append": "",
                    "maxlength": ""
                },
                {
                    "key": "field_62dec4147bf6f",
                    "label": "Value Text",
                    "name": "value_text",
                    "type": "text",
                    "instructions": "",
                    "required": 0,
                    "conditional_logic": 0,
                    "wrapper": {
                        "width": "",
                        "class": "",
                        "id": ""
                    },
                    "default_value": "",
                    "placeholder": "",
                    "prepend": "",
                    "append": "",
                    "maxlength": ""
                },
                {
                    "key": "field_62dec4357bf70",
                    "label": "Description",
                    "name": "description",
                    "type": "text",
                    "instructions": "",
                    "required": 0,
                    "conditional_logic": 0,
                    "wrapper": {
                        "width": "",
                        "class": "",
                        "id": ""
                    },
                    "default_value": "",
                    "placeholder": "",
                    "prepend": "",
                    "append": "",
                    "maxlength": ""
                }
            ]
        }
    ],
    "location": [
        [
            {
                "param": "block",
                "operator": "==",
                "value": "acf\/stats"
            }
        ]
    ],
    "menu_order": 0,
    "position": "normal",
    "style": "default",
    "label_placement": "top",
    "instruction_placement": "label",
    "hide_on_screen": "",
    "active": true,
    "description": "",
    "show_in_rest": 0,
    "modified": 1658767942
}